{
  "scriptId": "80",
  "url": "file:///Users/ludwig/Workspace/site-bender/deno-builder/src/elements/createTableHeadingCellConfig/mod.test.ts",
  "functions": [
    {
      "functionName": "",
      "ranges": [{ "startOffset": 0, "endOffset": 4298, "count": 1 }],
      "isBlockCoverage": true
    },
    {
      "functionName": "",
      "ranges": [{ "startOffset": 218, "endOffset": 533, "count": 1 }],
      "isBlockCoverage": true
    },
    {
      "functionName": "",
      "ranges": [{ "startOffset": 620, "endOffset": 1257, "count": 1 }],
      "isBlockCoverage": true
    }
  ]
}
